hydrotools/__init__.py
hydrotools/_version.py
hydrotools-3.1.0.dist-info/licenses/LICENSE
hydrotools-3.1.0.dist-info/licenses/NOTICE
hydrotools-3.1.0.dist-info/METADATA
hydrotools-3.1.0.dist-info/WHEEL
hydrotools-3.1.0.dist-info/top_level.txt
hydrotools-3.1.0.dist-info/RECORD
