Metadata-Version: 2.4
Name: hydrotools
Version: 3.1.0
Summary: Suite of tools for retrieving USGS NWIS observations and evaluating National Water Model (NWM) data.
Author-email: "Jason A. Regina" <jason.regina@noaa.gov>, Austin Raney <austin.raney@noaa.gov>
License: 
Project-URL: Homepage, https://github.com/NOAA-OWP/hydrotools
Project-URL: Documentation, https://noaa-owp.github.io/hydrotools
Project-URL: Repository, https://github.com/NOAA-OWP/hydrotools
Project-URL: Bug Tracker, https://github.com/NOAA-OWP/hydrotools/issues
Classifier: Development Status :: 5 - Production/Stable
Classifier: Intended Audience :: Education
Classifier: Intended Audience :: Science/Research
Classifier: License :: OSI Approved :: Apache Software License
Classifier: Programming Language :: Python :: 3.9
Classifier: Programming Language :: Python :: 3.10
Classifier: Programming Language :: Python :: 3.11
Classifier: Programming Language :: Python :: 3.12
Classifier: Topic :: Scientific/Engineering :: Hydrology
Classifier: Operating System :: OS Independent
Requires-Python: >=3.9
License-File: LICENSE
License-File: NOTICE
Requires-Dist: hydrotools.nwis_client==4.1.0
Requires-Dist: hydrotools.nwm_client==9.1.0
Requires-Dist: hydrotools.events==2.2.0
Requires-Dist: hydrotools.metrics==2.2.0
Requires-Dist: hydrotools.svi_client==1.1.0
Provides-Extra: develop
Requires-Dist: pytest; extra == "develop"
Dynamic: license-file
